TournamentFetcher/Tournament.py
TournamentFetcher/TournamentFetcher.py
TournamentFetcher/TournamentMatch.py
TournamentFetcher/TournamentParticipant.py
TournamentFetcher/__init__.py
TournamentFetcher-0.2.1.dist-info/LICENSE
TournamentFetcher-0.2.1.dist-info/METADATA
TournamentFetcher-0.2.1.dist-info/WHEEL
TournamentFetcher-0.2.1.dist-info/top_level.txt
TournamentFetcher-0.2.1.dist-info/RECORD
