Metadata-Version: 2.1
Name: TournamentFetcher
Version: 0.2.1
Summary: A Challonge and Smash.gg API wrapper with pandas support.
Home-page: https://github.com/Impasse52/TournamentFetcher
Author: Impasse52
License: UNKNOWN
Platform: UNKNOWN
License-File: LICENSE
